graphor/__init__.py
graphor/_base_client.py
graphor/_client.py
graphor/_compat.py
graphor/_constants.py
graphor/_exceptions.py
graphor/_files.py
graphor/_models.py
graphor/_qs.py
graphor/_resource.py
graphor/_response.py
graphor/_streaming.py
graphor/_types.py
graphor/_version.py
graphor/py.typed
graphor/_utils/__init__.py
graphor/_utils/_compat.py
graphor/_utils/_datetime_parse.py
graphor/_utils/_logs.py
graphor/_utils/_proxy.py
graphor/_utils/_reflection.py
graphor/_utils/_resources_proxy.py
graphor/_utils/_streams.py
graphor/_utils/_sync.py
graphor/_utils/_transform.py
graphor/_utils/_typing.py
graphor/_utils/_utils.py
graphor/lib/.keep
graphor/resources/__init__.py
graphor/resources/sources.py
graphor/types/__init__.py
graphor/types/partition_method.py
graphor/types/public_source.py
graphor/types/source_ask_params.py
graphor/types/source_ask_response.py
graphor/types/source_delete_params.py
graphor/types/source_delete_response.py
graphor/types/source_extract_params.py
graphor/types/source_extract_response.py
graphor/types/source_list_response.py
graphor/types/source_load_elements_params.py
graphor/types/source_load_elements_response.py
graphor/types/source_parse_params.py
graphor/types/source_retrieve_chunks_params.py
graphor/types/source_retrieve_chunks_response.py
graphor/types/source_upload_github_params.py
graphor/types/source_upload_params.py
graphor/types/source_upload_url_params.py
graphor/types/source_upload_youtube_params.py
graphor-0.2.2.dist-info/METADATA
graphor-0.2.2.dist-info/WHEEL
graphor-0.2.2.dist-info/licenses/LICENSE
graphor-0.2.2.dist-info/RECORD
